{
    "id": "90724043-c2bf-4443-852f-0d13d8618a93",
    "input_log": {
        "id": "72443360-50a9-4c5e-9177-c08f9ffca53a",
        "query": "SpaceX rocketfuel type",
        "start_date": null,
        "end_date": null,
        "return_json": true,
        "max_articles": 5,
        "time_stamp": "2024-09-23 20:17:43"
    },
    "output_logs": [
        {
            "id": "209424fb-b28f-47f3-b18a-8659c4b317e8",
            "articles": [
                {
                    "query": "OpenAI",
                    "start_date": null,
                    "end_date": null,
                    "formatted_result": "News Articles for OpenAI:\n\n\nArticle 1:\nTitle: OpenAI staffers reportedly 'taken aback' by 'ominous' logo rebranding\nDescription: OpenAI could undergo massive changes next year, which include getting a brand new logo. According to Fortune, though, staff members were less than enthused when they got a sneak peek of its supposed new logo at a recent company-wide meeting. The company's hex…\nURL: https://consent.yahoo.com/v2/collectConsent?sessionId=1_cc-session_9b62c213-d37b-493c-b44e-7c1f644485b4\nPublished At: 2024-09-21T16:00:17Z\nSource: Yahoo Entertainment\n\n\nArticle 2:\nTitle: OpenAI Messed With the Wrong Mega-Popular Parenting Forum\nDescription: Mumsnet CEO Justine Roberts spoke to WIRED about why licensing talks with OpenAI broke down and why her company is planning legal action.\nURL: https://www.wired.com/story/mumsnet-openai-copyright-allegations/\nPublished At: 2024-09-16T11:30:00Z\nSource: Wired\n\n\nArticle 3:\nTitle: OpenAI Announces a Model That ‘Reasons’ Through Problems, Calling It a ‘New Paradigm’\nDescription: The ChatGPT maker reveals details of OpenAI-o1, internally code-named Strawberry, which shows that AI needs more than scale to advance.\nURL: https://www.wired.com/story/openai-o1-strawberry-problem-reasoning/\nPublished At: 2024-09-12T17:05:00Z\nSource: Wired\n\n\nArticle 4:\nTitle: OpenAI's new o1 model is slower, on purpose\nDescription: OpenAI has unveiled its latest artificial intelligence model called o1, which, the company claims, can perform complex reasoning tasks more effectively than its predecessors. The release comes as OpenAI faces increasing competition in the race to develop more…\nURL: https://consent.yahoo.com/v2/collectConsent?sessionId=1_cc-session_dd64e3d9-b996-40ab-8407-741dc169ddb0\nPublished At: 2024-09-12T18:57:11Z\nSource: Yahoo Entertainment\n\n\nArticle 5:\nTitle: [Removed]\nDescription: [Removed]\nURL: https://removed.com\nPublished At: 2024-08-29T23:30:37Z\nSource: [Removed]\n\n",
                    "articles": [
                        {
                            "title": "OpenAI staffers reportedly 'taken aback' by 'ominous' logo rebranding",
                            "description": "OpenAI could undergo massive changes next year, which include getting a brand new logo. According to Fortune, though, staff members were less than enthused when they got a sneak peek of its supposed new logo at a recent company-wide meeting. The company's hex…",
                            "url": "https://consent.yahoo.com/v2/collectConsent?sessionId=1_cc-session_9b62c213-d37b-493c-b44e-7c1f644485b4",
                            "published_at": "2024-09-21T16:00:17Z",
                            "source": "Yahoo Entertainment"
                        },
                        {
                            "title": "OpenAI Messed With the Wrong Mega-Popular Parenting Forum",
                            "description": "Mumsnet CEO Justine Roberts spoke to WIRED about why licensing talks with OpenAI broke down and why her company is planning legal action.",
                            "url": "https://www.wired.com/story/mumsnet-openai-copyright-allegations/",
                            "published_at": "2024-09-16T11:30:00Z",
                            "source": "Wired"
                        },
                        {
                            "title": "OpenAI Announces a Model That ‘Reasons’ Through Problems, Calling It a ‘New Paradigm’",
                            "description": "The ChatGPT maker reveals details of OpenAI-o1, internally code-named Strawberry, which shows that AI needs more than scale to advance.",
                            "url": "https://www.wired.com/story/openai-o1-strawberry-problem-reasoning/",
                            "published_at": "2024-09-12T17:05:00Z",
                            "source": "Wired"
                        },
                        {
                            "title": "OpenAI's new o1 model is slower, on purpose",
                            "description": "OpenAI has unveiled its latest artificial intelligence model called o1, which, the company claims, can perform complex reasoning tasks more effectively than its predecessors. The release comes as OpenAI faces increasing competition in the race to develop more…",
                            "url": "https://consent.yahoo.com/v2/collectConsent?sessionId=1_cc-session_dd64e3d9-b996-40ab-8407-741dc169ddb0",
                            "published_at": "2024-09-12T18:57:11Z",
                            "source": "Yahoo Entertainment"
                        },
                        {
                            "title": "[Removed]",
                            "description": "[Removed]",
                            "url": "https://removed.com",
                            "published_at": "2024-08-29T23:30:37Z",
                            "source": "[Removed]"
                        }
                    ]
                }
            ],
            "summary": "Here are the latest news articles related to OpenAI:\n\n1. **OpenAI staffers reportedly 'taken aback' by 'ominous' logo rebranding**  \n   *Published on: September 21, 2024*  \n   OpenAI could undergo massive changes next year, which include getting a brand new logo. According to Fortune, staff members were less than enthused when they got a sneak peek of its supposed new logo at a recent company-wide meeting.  \n   [Read more](https://consent.yahoo.com/v2/collectConsent?sessionId=1_cc-session_9b62c213-d37b-493c-b44e-7c1f644485b4)\n\n2. **OpenAI Messed With the Wrong Mega-Popular Parenting Forum**  \n   *Published on: September 16, 2024*  \n   Mumsnet CEO Justine Roberts spoke to WIRED about why licensing talks with OpenAI broke down and why her company is planning legal action.  \n   [Read more](https://www.wired.com/story/mumsnet-openai-copyright-allegations/)\n\n3. **OpenAI Announces a Model That ‘Reasons’ Through Problems, Calling It a ‘New Paradigm’**  \n   *Published on: September 12, 2024*  \n   The ChatGPT maker reveals details of OpenAI-o1, internally code-named Strawberry, which shows that AI needs more than scale to advance.  \n   [Read more](https://www.wired.com/story/openai-o1-strawberry-problem-reasoning/)\n\n4. **OpenAI's new o1 model is slower, on purpose**  \n   *Published on: September 12, 2024*  \n   OpenAI has unveiled its latest artificial intelligence model called o1, which, the company claims, can perform complex reasoning tasks more effectively than its predecessors. The release comes as OpenAI faces increasing competition in the race to develop more advanced AI.  \n   [Read more](https://consent.yahoo.com/v2/collectConsent?sessionId=1_cc-session_dd64e3d9-b996-40ab-8407-741dc169ddb0)\n\nIf you need further details or a summary of any specific article, let me know!",
            "time_stamp": "2024-09-23 20:17:43"
        },
        {
            "id": "209424fb-b28f-47f3-b18a-8659c4b317e8",
            "articles": [
                {
                    "query": "Anthropic",
                    "start_date": null,
                    "end_date": null,
                    "formatted_result": "News Articles for Anthropic:\n\n\nArticle 1:\nTitle: [Removed]\nDescription: [Removed]\nURL: https://removed.com\nPublished At: 2024-09-12T19:15:36Z\nSource: [Removed]\n\n\nArticle 2:\nTitle: Anthropic Publishes the 'System Prompts' That Make Claude Tick\nDescription: An anonymous reader quotes a report from TechCrunch: [...] Anthropic, in its continued effort to paint itself as a more ethical, transparent AI vendor, has published the system prompts for its latest models (Claude 3 Opus, Claude 3.5 Sonnet and Claude 3 Haiku…\nURL: https://slashdot.org/story/24/08/27/2140245/anthropic-publishes-the-system-prompts-that-make-claude-tick\nPublished At: 2024-08-27T23:30:00Z\nSource: Slashdot.org\n\n\nArticle 3:\nTitle: Amazon Is Reportedly Closer to Launching Paid Alexa\nDescription: The \"Remarkable\" version of Amazon's digital assistant will tap into Anthropic's Claude AI.\nURL: https://gizmodo.com/amazon-is-reportedly-closer-to-launching-paid-alexa-2000493406\nPublished At: 2024-08-30T19:00:47Z\nSource: Gizmodo.com\n\n\nArticle 4:\nTitle: Anthropic launches Claude Artifacts generally for all users, mobile\nDescription: Only Free and Pro plans will have the ability to publish and remix Artifacts with the broader Claude community.\nURL: https://venturebeat.com/ai/anthropic-launches-claude-artifacts-generally-for-all-users-mobile/\nPublished At: 2024-08-27T22:15:00Z\nSource: VentureBeat\n\n\nArticle 5:\nTitle: Like digital locusts, OpenAI and Anthropic AI bots cause havoc and raise costs for websites\nDescription: AI giants send bots out to crawl the web and scrape data for free. Adding insult to injury, the bots are disrupting websites and spiking cloud bills.\nURL: https://www.businessinsider.com/openai-anthropic-ai-bots-havoc-raise-cloud-costs-websites-2024-9\nPublished At: 2024-09-19T09:00:02Z\nSource: Business Insider\n\n",
                    "articles": [
                        {
                            "title": "[Removed]",
                            "description": "[Removed]",
                            "url": "https://removed.com",
                            "published_at": "2024-09-12T19:15:36Z",
                            "source": "[Removed]"
                        },
                        {
                            "title": "Anthropic Publishes the 'System Prompts' That Make Claude Tick",
                            "description": "An anonymous reader quotes a report from TechCrunch: [...] Anthropic, in its continued effort to paint itself as a more ethical, transparent AI vendor, has published the system prompts for its latest models (Claude 3 Opus, Claude 3.5 Sonnet and Claude 3 Haiku…",
                            "url": "https://slashdot.org/story/24/08/27/2140245/anthropic-publishes-the-system-prompts-that-make-claude-tick",
                            "published_at": "2024-08-27T23:30:00Z",
                            "source": "Slashdot.org"
                        },
                        {
                            "title": "Amazon Is Reportedly Closer to Launching Paid Alexa",
                            "description": "The \"Remarkable\" version of Amazon's digital assistant will tap into Anthropic's Claude AI.",
                            "url": "https://gizmodo.com/amazon-is-reportedly-closer-to-launching-paid-alexa-2000493406",
                            "published_at": "2024-08-30T19:00:47Z",
                            "source": "Gizmodo.com"
                        },
                        {
                            "title": "Anthropic launches Claude Artifacts generally for all users, mobile",
                            "description": "Only Free and Pro plans will have the ability to publish and remix Artifacts with the broader Claude community.",
                            "url": "https://venturebeat.com/ai/anthropic-launches-claude-artifacts-generally-for-all-users-mobile/",
                            "published_at": "2024-08-27T22:15:00Z",
                            "source": "VentureBeat"
                        },
                        {
                            "title": "Like digital locusts, OpenAI and Anthropic AI bots cause havoc and raise costs for websites",
                            "description": "AI giants send bots out to crawl the web and scrape data for free. Adding insult to injury, the bots are disrupting websites and spiking cloud bills.",
                            "url": "https://www.businessinsider.com/openai-anthropic-ai-bots-havoc-raise-cloud-costs-websites-2024-9",
                            "published_at": "2024-09-19T09:00:02Z",
                            "source": "Business Insider"
                        }
                    ]
                }
            ],
            "summary": "Here are the latest news articles related to Anthropic:\n\n1. **Anthropic Publishes the 'System Prompts' That Make Claude Tick**  \n   *Published on: August 27, 2024*  \n   Anthropic has published the system prompts for its latest models (Claude 3 Opus, Claude 3.5 Sonnet, and Claude 3 Haiku) as part of its effort to present itself as a more ethical and transparent AI vendor.  \n   [Read more](https://slashdot.org/story/24/08/27/2140245/anthropic-publishes-the-system-prompts-that-make-claude-tick)\n\n2. **Amazon Is Reportedly Closer to Launching Paid Alexa**  \n   *Published on: August 30, 2024*  \n   The \"Remarkable\" version of Amazon's digital assistant will utilize Anthropic's Claude AI, indicating a significant partnership between the two companies.  \n   [Read more](https://gizmodo.com/amazon-is-reportedly-closer-to-launching-paid-alexa-2000493406)\n\n3. **Anthropic launches Claude Artifacts generally for all users, mobile**  \n   *Published on: August 27, 2024*  \n   Anthropic has made Claude Artifacts available to all users, allowing Free and Pro plan subscribers to publish and remix Artifacts within the Claude community.  \n   [Read more](https://venturebeat.com/ai/anthropic-launches-claude-artifacts-generally-for-all-users-mobile/)\n\n4. **Like digital locusts, OpenAI and Anthropic AI bots cause havoc and raise costs for websites**  \n   *Published on: September 19, 2024*  \n   AI bots from OpenAI and Anthropic are reportedly causing disruptions on websites and increasing cloud costs due to their web crawling activities.  \n   [Read more](https://www.businessinsider.com/openai-anthropic-ai-bots-havoc-raise-cloud-costs-websites-2024-9)\n\nIf you need more information or a summary of any specific article, feel free to ask!",
            "time_stamp": "2024-09-23 20:17:43"
        },
        {
            "id": "209424fb-b28f-47f3-b18a-8659c4b317e8",
            "articles": [
                "o",
                " ",
                "a",
                "r",
                "t",
                "i",
                "c",
                "l",
                "e",
                "s",
                " ",
                "f",
                "o",
                "u",
                "n",
                "d",
                " ",
                "f",
                "o",
                "r",
                " ",
                "t",
                "h",
                "e",
                " ",
                "g",
                "i",
                "v",
                "e",
                "n",
                " ",
                "q",
                "u",
                "e",
                "r",
                "y",
                " ",
                "a",
                "n",
                "d",
                " ",
                "d",
                "a",
                "t",
                "e",
                " ",
                "r",
                "a",
                "n",
                "g",
                "e",
                "."
            ],
            "summary": "It seems that you've sent a command without any specific request or context. How can I assist you today? If you need information, summaries, or help with tasks related to the news articles or anything else, just let me know!",
            "time_stamp": "2024-09-23 20:17:43"
        }
    ],
    "time_stamp": "2024-09-23 20:17:43"
}