{
    "id": "731531cf-7575-4379-b343-06abea0dcddf",
    "input_log": {
        "id": "0144da37-dff6-430f-9b57-3e0ea2203f18",
        "query": "Anthropic",
        "start_date": null,
        "end_date": null,
        "return_json": true,
        "max_articles": 5,
        "time_stamp": "2024-09-23 20:26:47"
    },
    "output_logs": [
        {
            "id": "7d925c6f-3007-42a9-87c3-c0c9db1e8abc",
            "articles": [
                {
                    "query": "multi-agent collaboration",
                    "start_date": null,
                    "end_date": null,
                    "formatted_result": "News Articles for multi-agent collaboration:\n\n\nArticle 1:\nTitle: MK2 Films Sets Major Slate Financing Deal With IPR.VC\nDescription: European sales, production and finance company mk2 films has announced a multi-year slate financing deal with investment fund manager IPR.VC, which will provide “significant financial backing for a slate of future projects”.  “We are thrilled to work with IPR…\nURL: http://deadline.com/2024/09/mk2-films-major-slate-financing-deal-with-ipr-vc-1236094037/\nPublished At: 2024-09-19T12:00:12Z\nSource: Deadline\n\n\nArticle 2:\nTitle: Introducing SEOntology: The Future Of SEO In The Age Of AI via @sejournal, @cyberandy\nDescription: SEOntology is more than a technical framework. Gain rich insights - learn to standardize SEO data and practices to build a sustainable future with GenAI.\nThe post Introducing SEOntology: The Future Of SEO In The Age Of AI appeared first on Search Engine Journ…\nURL: https://www.searchenginejournal.com/introducing-seontology-the-future-of-seo-in-the-age-of-ai/524773/\nPublished At: 2024-08-27T13:02:05Z\nSource: Search Engine Journal\n\n\nArticle 3:\nTitle: Multi-Agent System’s Architecture\nDescription: The distribution of decision-making and interaction among the various agents that make up the system principally distinguishes multi-agent systems from single-agent systems. In a single-agent system, a centralized agent makes all decisions, with other agents …\nURL: https://generativeai.pub/multi-agent-systems-architecture-d07227b3059b\nPublished At: 2024-08-26T16:00:03Z\nSource: Generativeai.pub\n\n\nArticle 4:\nTitle: Support Engineering In The Age Of Cloud Computing: Navigating Challenges And Embracing Opportunities\nDescription: Let's explore the intricacies of support engineering in the cloud era and look at how professionals can navigate the complexities and leverage emerging opportunities.\nURL: https://www.forbes.com/councils/forbestechcouncil/2024/09/17/support-engineering-in-the-age-of-cloud-computing-navigating-challenges-and-embracing-opportunities/\nPublished At: 2024-09-17T12:45:00Z\nSource: Forbes\n\n\nArticle 5:\nTitle: AI Unlocks NCAA’s Video Vault: Athletes To Cash In On NIL Deals Using 90+ Years Of Game Footage\nDescription: AI has entered the chat for NCAA video creating new revenue opportunities for college athletes.\nURL: https://www.forbes.com/sites/karenweaver/2024/09/05/ai-unlocks-ncaas-video-vault-athletes-to-cash-in-on-nil-deals-using-90-years-of-game-footage/\nPublished At: 2024-09-05T19:44:41Z\nSource: Forbes\n\n",
                    "articles": [
                        {
                            "title": "MK2 Films Sets Major Slate Financing Deal With IPR.VC",
                            "description": "European sales, production and finance company mk2 films has announced a multi-year slate financing deal with investment fund manager IPR.VC, which will provide “significant financial backing for a slate of future projects”.  “We are thrilled to work with IPR…",
                            "url": "http://deadline.com/2024/09/mk2-films-major-slate-financing-deal-with-ipr-vc-1236094037/",
                            "published_at": "2024-09-19T12:00:12Z",
                            "source": "Deadline"
                        },
                        {
                            "title": "Introducing SEOntology: The Future Of SEO In The Age Of AI via @sejournal, @cyberandy",
                            "description": "SEOntology is more than a technical framework. Gain rich insights - learn to standardize SEO data and practices to build a sustainable future with GenAI.\nThe post Introducing SEOntology: The Future Of SEO In The Age Of AI appeared first on Search Engine Journ…",
                            "url": "https://www.searchenginejournal.com/introducing-seontology-the-future-of-seo-in-the-age-of-ai/524773/",
                            "published_at": "2024-08-27T13:02:05Z",
                            "source": "Search Engine Journal"
                        },
                        {
                            "title": "Multi-Agent System’s Architecture",
                            "description": "The distribution of decision-making and interaction among the various agents that make up the system principally distinguishes multi-agent systems from single-agent systems. In a single-agent system, a centralized agent makes all decisions, with other agents …",
                            "url": "https://generativeai.pub/multi-agent-systems-architecture-d07227b3059b",
                            "published_at": "2024-08-26T16:00:03Z",
                            "source": "Generativeai.pub"
                        },
                        {
                            "title": "Support Engineering In The Age Of Cloud Computing: Navigating Challenges And Embracing Opportunities",
                            "description": "Let's explore the intricacies of support engineering in the cloud era and look at how professionals can navigate the complexities and leverage emerging opportunities.",
                            "url": "https://www.forbes.com/councils/forbestechcouncil/2024/09/17/support-engineering-in-the-age-of-cloud-computing-navigating-challenges-and-embracing-opportunities/",
                            "published_at": "2024-09-17T12:45:00Z",
                            "source": "Forbes"
                        },
                        {
                            "title": "AI Unlocks NCAA’s Video Vault: Athletes To Cash In On NIL Deals Using 90+ Years Of Game Footage",
                            "description": "AI has entered the chat for NCAA video creating new revenue opportunities for college athletes.",
                            "url": "https://www.forbes.com/sites/karenweaver/2024/09/05/ai-unlocks-ncaas-video-vault-athletes-to-cash-in-on-nil-deals-using-90-years-of-game-footage/",
                            "published_at": "2024-09-05T19:44:41Z",
                            "source": "Forbes"
                        }
                    ]
                }
            ],
            "summary": "Based on the provided articles, it seems you're interested in multi-agent collaboration, the intersection of AI and various industries, and recent developments in financing and technology. Here are some potential tasks or workflows we can automate or explore further:\n\n1. **Summarization of Articles**: Create concise summaries for each article to quickly understand their key points.\n\n2. **Content Aggregation**: Compile articles related to a specific topic, such as multi-agent systems or AI advancements, into a single document for easy reference.\n\n3. **Trend Analysis**: Analyze the articles for trends related to AI, finance, and technology, identifying key themes and emerging opportunities.\n\n4. **Collaboration Framework**: Develop a framework for how multi-agent systems can be effectively utilized in various industries, based on insights from the articles.\n\n5. **SEO Strategy Development**: Use insights from the article on SEOntology to create a strategic plan for improving SEO in a specific context.\n\nWould you like to proceed with any of these tasks or explore something else?",
            "time_stamp": "2024-09-23 20:26:47"
        },
        {
            "id": "7d925c6f-3007-42a9-87c3-c0c9db1e8abc",
            "articles": [
                {
                    "query": "OpenAI",
                    "start_date": null,
                    "end_date": null,
                    "formatted_result": "News Articles for OpenAI:\n\n\nArticle 1:\nTitle: OpenAI staffers reportedly 'taken aback' by 'ominous' logo rebranding\nDescription: OpenAI could undergo massive changes next year, which include getting a brand new logo. According to Fortune, though, staff members were less than enthused when they got a sneak peek of its supposed new logo at a recent company-wide meeting. The company's hex…\nURL: https://consent.yahoo.com/v2/collectConsent?sessionId=1_cc-session_9b62c213-d37b-493c-b44e-7c1f644485b4\nPublished At: 2024-09-21T16:00:17Z\nSource: Yahoo Entertainment\n\n\nArticle 2:\nTitle: OpenAI Messed With the Wrong Mega-Popular Parenting Forum\nDescription: Mumsnet CEO Justine Roberts spoke to WIRED about why licensing talks with OpenAI broke down and why her company is planning legal action.\nURL: https://www.wired.com/story/mumsnet-openai-copyright-allegations/\nPublished At: 2024-09-16T11:30:00Z\nSource: Wired\n\n\nArticle 3:\nTitle: OpenAI Announces a Model That ‘Reasons’ Through Problems, Calling It a ‘New Paradigm’\nDescription: The ChatGPT maker reveals details of OpenAI-o1, internally code-named Strawberry, which shows that AI needs more than scale to advance.\nURL: https://www.wired.com/story/openai-o1-strawberry-problem-reasoning/\nPublished At: 2024-09-12T17:05:00Z\nSource: Wired\n\n\nArticle 4:\nTitle: OpenAI's new o1 model is slower, on purpose\nDescription: OpenAI has unveiled its latest artificial intelligence model called o1, which, the company claims, can perform complex reasoning tasks more effectively than its predecessors. The release comes as OpenAI faces increasing competition in the race to develop more…\nURL: https://consent.yahoo.com/v2/collectConsent?sessionId=1_cc-session_dd64e3d9-b996-40ab-8407-741dc169ddb0\nPublished At: 2024-09-12T18:57:11Z\nSource: Yahoo Entertainment\n\n\nArticle 5:\nTitle: [Removed]\nDescription: [Removed]\nURL: https://removed.com\nPublished At: 2024-08-29T23:30:37Z\nSource: [Removed]\n\n",
                    "articles": [
                        {
                            "title": "OpenAI staffers reportedly 'taken aback' by 'ominous' logo rebranding",
                            "description": "OpenAI could undergo massive changes next year, which include getting a brand new logo. According to Fortune, though, staff members were less than enthused when they got a sneak peek of its supposed new logo at a recent company-wide meeting. The company's hex…",
                            "url": "https://consent.yahoo.com/v2/collectConsent?sessionId=1_cc-session_9b62c213-d37b-493c-b44e-7c1f644485b4",
                            "published_at": "2024-09-21T16:00:17Z",
                            "source": "Yahoo Entertainment"
                        },
                        {
                            "title": "OpenAI Messed With the Wrong Mega-Popular Parenting Forum",
                            "description": "Mumsnet CEO Justine Roberts spoke to WIRED about why licensing talks with OpenAI broke down and why her company is planning legal action.",
                            "url": "https://www.wired.com/story/mumsnet-openai-copyright-allegations/",
                            "published_at": "2024-09-16T11:30:00Z",
                            "source": "Wired"
                        },
                        {
                            "title": "OpenAI Announces a Model That ‘Reasons’ Through Problems, Calling It a ‘New Paradigm’",
                            "description": "The ChatGPT maker reveals details of OpenAI-o1, internally code-named Strawberry, which shows that AI needs more than scale to advance.",
                            "url": "https://www.wired.com/story/openai-o1-strawberry-problem-reasoning/",
                            "published_at": "2024-09-12T17:05:00Z",
                            "source": "Wired"
                        },
                        {
                            "title": "OpenAI's new o1 model is slower, on purpose",
                            "description": "OpenAI has unveiled its latest artificial intelligence model called o1, which, the company claims, can perform complex reasoning tasks more effectively than its predecessors. The release comes as OpenAI faces increasing competition in the race to develop more…",
                            "url": "https://consent.yahoo.com/v2/collectConsent?sessionId=1_cc-session_dd64e3d9-b996-40ab-8407-741dc169ddb0",
                            "published_at": "2024-09-12T18:57:11Z",
                            "source": "Yahoo Entertainment"
                        },
                        {
                            "title": "[Removed]",
                            "description": "[Removed]",
                            "url": "https://removed.com",
                            "published_at": "2024-08-29T23:30:37Z",
                            "source": "[Removed]"
                        }
                    ]
                }
            ],
            "summary": "Based on the recent articles related to OpenAI, here are some tasks we can automate or explore further:\n\n1. **Summarization of OpenAI Articles**: Create concise summaries for each article to highlight key developments and insights about OpenAI.\n\n2. **Reputation Monitoring**: Track and analyze public sentiment regarding OpenAI's recent changes, including the logo rebranding and legal issues with Mumsnet.\n\n3. **Model Comparison**: Develop a comparison of OpenAI's new o1 model with previous models, focusing on performance, reasoning capabilities, and speed.\n\n4. **Legal Analysis**: Summarize the legal implications of the licensing talks between OpenAI and Mumsnet, including potential outcomes and industry impact.\n\n5. **Trend Analysis in AI Development**: Analyze trends in AI development as indicated by OpenAI's announcements, particularly in relation to reasoning capabilities and competition in the market.\n\nWould you like to proceed with any of these tasks or explore something else?",
            "time_stamp": "2024-09-23 20:26:47"
        },
        {
            "id": "7d925c6f-3007-42a9-87c3-c0c9db1e8abc",
            "articles": [
                {
                    "query": "Anthropic",
                    "start_date": null,
                    "end_date": null,
                    "formatted_result": "News Articles for Anthropic:\n\n\nArticle 1:\nTitle: [Removed]\nDescription: [Removed]\nURL: https://removed.com\nPublished At: 2024-09-12T19:15:36Z\nSource: [Removed]\n\n\nArticle 2:\nTitle: Anthropic Publishes the 'System Prompts' That Make Claude Tick\nDescription: An anonymous reader quotes a report from TechCrunch: [...] Anthropic, in its continued effort to paint itself as a more ethical, transparent AI vendor, has published the system prompts for its latest models (Claude 3 Opus, Claude 3.5 Sonnet and Claude 3 Haiku…\nURL: https://slashdot.org/story/24/08/27/2140245/anthropic-publishes-the-system-prompts-that-make-claude-tick\nPublished At: 2024-08-27T23:30:00Z\nSource: Slashdot.org\n\n\nArticle 3:\nTitle: Amazon Is Reportedly Closer to Launching Paid Alexa\nDescription: The \"Remarkable\" version of Amazon's digital assistant will tap into Anthropic's Claude AI.\nURL: https://gizmodo.com/amazon-is-reportedly-closer-to-launching-paid-alexa-2000493406\nPublished At: 2024-08-30T19:00:47Z\nSource: Gizmodo.com\n\n\nArticle 4:\nTitle: Anthropic launches Claude Artifacts generally for all users, mobile\nDescription: Only Free and Pro plans will have the ability to publish and remix Artifacts with the broader Claude community.\nURL: https://venturebeat.com/ai/anthropic-launches-claude-artifacts-generally-for-all-users-mobile/\nPublished At: 2024-08-27T22:15:00Z\nSource: VentureBeat\n\n\nArticle 5:\nTitle: Like digital locusts, OpenAI and Anthropic AI bots cause havoc and raise costs for websites\nDescription: AI giants send bots out to crawl the web and scrape data for free. Adding insult to injury, the bots are disrupting websites and spiking cloud bills.\nURL: https://www.businessinsider.com/openai-anthropic-ai-bots-havoc-raise-cloud-costs-websites-2024-9\nPublished At: 2024-09-19T09:00:02Z\nSource: Business Insider\n\n",
                    "articles": [
                        {
                            "title": "[Removed]",
                            "description": "[Removed]",
                            "url": "https://removed.com",
                            "published_at": "2024-09-12T19:15:36Z",
                            "source": "[Removed]"
                        },
                        {
                            "title": "Anthropic Publishes the 'System Prompts' That Make Claude Tick",
                            "description": "An anonymous reader quotes a report from TechCrunch: [...] Anthropic, in its continued effort to paint itself as a more ethical, transparent AI vendor, has published the system prompts for its latest models (Claude 3 Opus, Claude 3.5 Sonnet and Claude 3 Haiku…",
                            "url": "https://slashdot.org/story/24/08/27/2140245/anthropic-publishes-the-system-prompts-that-make-claude-tick",
                            "published_at": "2024-08-27T23:30:00Z",
                            "source": "Slashdot.org"
                        },
                        {
                            "title": "Amazon Is Reportedly Closer to Launching Paid Alexa",
                            "description": "The \"Remarkable\" version of Amazon's digital assistant will tap into Anthropic's Claude AI.",
                            "url": "https://gizmodo.com/amazon-is-reportedly-closer-to-launching-paid-alexa-2000493406",
                            "published_at": "2024-08-30T19:00:47Z",
                            "source": "Gizmodo.com"
                        },
                        {
                            "title": "Anthropic launches Claude Artifacts generally for all users, mobile",
                            "description": "Only Free and Pro plans will have the ability to publish and remix Artifacts with the broader Claude community.",
                            "url": "https://venturebeat.com/ai/anthropic-launches-claude-artifacts-generally-for-all-users-mobile/",
                            "published_at": "2024-08-27T22:15:00Z",
                            "source": "VentureBeat"
                        },
                        {
                            "title": "Like digital locusts, OpenAI and Anthropic AI bots cause havoc and raise costs for websites",
                            "description": "AI giants send bots out to crawl the web and scrape data for free. Adding insult to injury, the bots are disrupting websites and spiking cloud bills.",
                            "url": "https://www.businessinsider.com/openai-anthropic-ai-bots-havoc-raise-cloud-costs-websites-2024-9",
                            "published_at": "2024-09-19T09:00:02Z",
                            "source": "Business Insider"
                        }
                    ]
                }
            ],
            "summary": "Based on the recent articles you've provided concerning OpenAI, Anthropic, and multi-agent systems, I can assist you in a variety of ways. Here are some possible tasks or workflows we can pursue:\n\n1. **Summarization of Articles**: I can distill the main points and key insights from the articles related to OpenAI and Anthropic to provide you with a quick overview.\n\n2. **Comparative Analysis**: We can examine the developments and strategies of OpenAI and Anthropic, highlighting their differences and similarities in AI approaches and product offerings.\n\n3. **Implications of AI Developments**: I'll analyze the potential impact of the new AI models and changes in branding on the industry and how they might affect user experiences.\n\n4. **Legal and Ethical Considerations**: Discuss the legal ramifications of the licensing issues between OpenAI and Mumsnet, as well as the ethical implications of AI data scraping as mentioned in the articles.\n\n5. **Multi-Agent Systems Insights**: Integrate information from the multi-agent systems article to explore how these concepts might relate to the development of AI agents by OpenAI and Anthropic.\n\nWould you like to dive into any of these areas, or do you have a different task in mind?",
            "time_stamp": "2024-09-23 20:26:47"
        }
    ],
    "time_stamp": "2024-09-23 20:26:47"
}