{
    "id": "4c87069a-b6ee-4da6-8054-19bcf6c34378",
    "input_log": {
        "id": "1eac83b2-c8d3-4668-9a29-d732e58bb933",
        "query": "SpaceX rocketfuel type",
        "start_date": null,
        "end_date": null,
        "return_json": true,
        "max_articles": 5,
        "time_stamp": "2024-09-23 20:20:50"
    },
    "output_logs": [
        {
            "id": "220e3f3d-bcad-4441-9a88-fcee13b883ac",
            "articles": [
                "o",
                " ",
                "a",
                "r",
                "t",
                "i",
                "c",
                "l",
                "e",
                "s",
                " ",
                "f",
                "o",
                "u",
                "n",
                "d",
                " ",
                "f",
                "o",
                "r",
                " ",
                "t",
                "h",
                "e",
                " ",
                "g",
                "i",
                "v",
                "e",
                "n",
                " ",
                "q",
                "u",
                "e",
                "r",
                "y",
                " ",
                "a",
                "n",
                "d",
                " ",
                "d",
                "a",
                "t",
                "e",
                " ",
                "r",
                "a",
                "n",
                "g",
                "e",
                "."
            ],
            "summary": "Hello! It seems like you're looking for assistance with automating tasks or workflows. How can I help you today? Do you have a specific task in mind that you'd like to automate?",
            "time_stamp": "2024-09-23 20:20:50"
        },
        {
            "id": "220e3f3d-bcad-4441-9a88-fcee13b883ac",
            "articles": [
                {
                    "query": "OpenAI",
                    "start_date": null,
                    "end_date": null,
                    "formatted_result": "News Articles for OpenAI:\n\n\nArticle 1:\nTitle: OpenAI staffers reportedly 'taken aback' by 'ominous' logo rebranding\nDescription: OpenAI could undergo massive changes next year, which include getting a brand new logo. According to Fortune, though, staff members were less than enthused when they got a sneak peek of its supposed new logo at a recent company-wide meeting. The company's hex…\nURL: https://consent.yahoo.com/v2/collectConsent?sessionId=1_cc-session_9b62c213-d37b-493c-b44e-7c1f644485b4\nPublished At: 2024-09-21T16:00:17Z\nSource: Yahoo Entertainment\n\n\nArticle 2:\nTitle: OpenAI Messed With the Wrong Mega-Popular Parenting Forum\nDescription: Mumsnet CEO Justine Roberts spoke to WIRED about why licensing talks with OpenAI broke down and why her company is planning legal action.\nURL: https://www.wired.com/story/mumsnet-openai-copyright-allegations/\nPublished At: 2024-09-16T11:30:00Z\nSource: Wired\n\n\nArticle 3:\nTitle: OpenAI Announces a Model That ‘Reasons’ Through Problems, Calling It a ‘New Paradigm’\nDescription: The ChatGPT maker reveals details of OpenAI-o1, internally code-named Strawberry, which shows that AI needs more than scale to advance.\nURL: https://www.wired.com/story/openai-o1-strawberry-problem-reasoning/\nPublished At: 2024-09-12T17:05:00Z\nSource: Wired\n\n\nArticle 4:\nTitle: OpenAI's new o1 model is slower, on purpose\nDescription: OpenAI has unveiled its latest artificial intelligence model called o1, which, the company claims, can perform complex reasoning tasks more effectively than its predecessors. The release comes as OpenAI faces increasing competition in the race to develop more…\nURL: https://consent.yahoo.com/v2/collectConsent?sessionId=1_cc-session_dd64e3d9-b996-40ab-8407-741dc169ddb0\nPublished At: 2024-09-12T18:57:11Z\nSource: Yahoo Entertainment\n\n\nArticle 5:\nTitle: [Removed]\nDescription: [Removed]\nURL: https://removed.com\nPublished At: 2024-08-29T23:30:37Z\nSource: [Removed]\n\n",
                    "articles": [
                        {
                            "title": "OpenAI staffers reportedly 'taken aback' by 'ominous' logo rebranding",
                            "description": "OpenAI could undergo massive changes next year, which include getting a brand new logo. According to Fortune, though, staff members were less than enthused when they got a sneak peek of its supposed new logo at a recent company-wide meeting. The company's hex…",
                            "url": "https://consent.yahoo.com/v2/collectConsent?sessionId=1_cc-session_9b62c213-d37b-493c-b44e-7c1f644485b4",
                            "published_at": "2024-09-21T16:00:17Z",
                            "source": "Yahoo Entertainment"
                        },
                        {
                            "title": "OpenAI Messed With the Wrong Mega-Popular Parenting Forum",
                            "description": "Mumsnet CEO Justine Roberts spoke to WIRED about why licensing talks with OpenAI broke down and why her company is planning legal action.",
                            "url": "https://www.wired.com/story/mumsnet-openai-copyright-allegations/",
                            "published_at": "2024-09-16T11:30:00Z",
                            "source": "Wired"
                        },
                        {
                            "title": "OpenAI Announces a Model That ‘Reasons’ Through Problems, Calling It a ‘New Paradigm’",
                            "description": "The ChatGPT maker reveals details of OpenAI-o1, internally code-named Strawberry, which shows that AI needs more than scale to advance.",
                            "url": "https://www.wired.com/story/openai-o1-strawberry-problem-reasoning/",
                            "published_at": "2024-09-12T17:05:00Z",
                            "source": "Wired"
                        },
                        {
                            "title": "OpenAI's new o1 model is slower, on purpose",
                            "description": "OpenAI has unveiled its latest artificial intelligence model called o1, which, the company claims, can perform complex reasoning tasks more effectively than its predecessors. The release comes as OpenAI faces increasing competition in the race to develop more…",
                            "url": "https://consent.yahoo.com/v2/collectConsent?sessionId=1_cc-session_dd64e3d9-b996-40ab-8407-741dc169ddb0",
                            "published_at": "2024-09-12T18:57:11Z",
                            "source": "Yahoo Entertainment"
                        },
                        {
                            "title": "[Removed]",
                            "description": "[Removed]",
                            "url": "https://removed.com",
                            "published_at": "2024-08-29T23:30:37Z",
                            "source": "[Removed]"
                        }
                    ]
                }
            ],
            "summary": "It looks like you've provided a list of recent news articles related to OpenAI. How can I assist you with this information? Would you like a summary of the articles, analysis, or perhaps help with a specific task related to them?",
            "time_stamp": "2024-09-23 20:20:50"
        },
        {
            "id": "220e3f3d-bcad-4441-9a88-fcee13b883ac",
            "articles": [
                {
                    "query": "Anthropic",
                    "start_date": null,
                    "end_date": null,
                    "formatted_result": "News Articles for Anthropic:\n\n\nArticle 1:\nTitle: [Removed]\nDescription: [Removed]\nURL: https://removed.com\nPublished At: 2024-09-12T19:15:36Z\nSource: [Removed]\n\n\nArticle 2:\nTitle: Anthropic Publishes the 'System Prompts' That Make Claude Tick\nDescription: An anonymous reader quotes a report from TechCrunch: [...] Anthropic, in its continued effort to paint itself as a more ethical, transparent AI vendor, has published the system prompts for its latest models (Claude 3 Opus, Claude 3.5 Sonnet and Claude 3 Haiku…\nURL: https://slashdot.org/story/24/08/27/2140245/anthropic-publishes-the-system-prompts-that-make-claude-tick\nPublished At: 2024-08-27T23:30:00Z\nSource: Slashdot.org\n\n\nArticle 3:\nTitle: Amazon Is Reportedly Closer to Launching Paid Alexa\nDescription: The \"Remarkable\" version of Amazon's digital assistant will tap into Anthropic's Claude AI.\nURL: https://gizmodo.com/amazon-is-reportedly-closer-to-launching-paid-alexa-2000493406\nPublished At: 2024-08-30T19:00:47Z\nSource: Gizmodo.com\n\n\nArticle 4:\nTitle: Anthropic launches Claude Artifacts generally for all users, mobile\nDescription: Only Free and Pro plans will have the ability to publish and remix Artifacts with the broader Claude community.\nURL: https://venturebeat.com/ai/anthropic-launches-claude-artifacts-generally-for-all-users-mobile/\nPublished At: 2024-08-27T22:15:00Z\nSource: VentureBeat\n\n\nArticle 5:\nTitle: Like digital locusts, OpenAI and Anthropic AI bots cause havoc and raise costs for websites\nDescription: AI giants send bots out to crawl the web and scrape data for free. Adding insult to injury, the bots are disrupting websites and spiking cloud bills.\nURL: https://www.businessinsider.com/openai-anthropic-ai-bots-havoc-raise-cloud-costs-websites-2024-9\nPublished At: 2024-09-19T09:00:02Z\nSource: Business Insider\n\n",
                    "articles": [
                        {
                            "title": "[Removed]",
                            "description": "[Removed]",
                            "url": "https://removed.com",
                            "published_at": "2024-09-12T19:15:36Z",
                            "source": "[Removed]"
                        },
                        {
                            "title": "Anthropic Publishes the 'System Prompts' That Make Claude Tick",
                            "description": "An anonymous reader quotes a report from TechCrunch: [...] Anthropic, in its continued effort to paint itself as a more ethical, transparent AI vendor, has published the system prompts for its latest models (Claude 3 Opus, Claude 3.5 Sonnet and Claude 3 Haiku…",
                            "url": "https://slashdot.org/story/24/08/27/2140245/anthropic-publishes-the-system-prompts-that-make-claude-tick",
                            "published_at": "2024-08-27T23:30:00Z",
                            "source": "Slashdot.org"
                        },
                        {
                            "title": "Amazon Is Reportedly Closer to Launching Paid Alexa",
                            "description": "The \"Remarkable\" version of Amazon's digital assistant will tap into Anthropic's Claude AI.",
                            "url": "https://gizmodo.com/amazon-is-reportedly-closer-to-launching-paid-alexa-2000493406",
                            "published_at": "2024-08-30T19:00:47Z",
                            "source": "Gizmodo.com"
                        },
                        {
                            "title": "Anthropic launches Claude Artifacts generally for all users, mobile",
                            "description": "Only Free and Pro plans will have the ability to publish and remix Artifacts with the broader Claude community.",
                            "url": "https://venturebeat.com/ai/anthropic-launches-claude-artifacts-generally-for-all-users-mobile/",
                            "published_at": "2024-08-27T22:15:00Z",
                            "source": "VentureBeat"
                        },
                        {
                            "title": "Like digital locusts, OpenAI and Anthropic AI bots cause havoc and raise costs for websites",
                            "description": "AI giants send bots out to crawl the web and scrape data for free. Adding insult to injury, the bots are disrupting websites and spiking cloud bills.",
                            "url": "https://www.businessinsider.com/openai-anthropic-ai-bots-havoc-raise-cloud-costs-websites-2024-9",
                            "published_at": "2024-09-19T09:00:02Z",
                            "source": "Business Insider"
                        }
                    ]
                }
            ],
            "summary": "It looks like you've provided a list of recent news articles related to OpenAI and Anthropic. How can I assist you with this information? Would you like a summary, analysis, or perhaps help in organizing this content for a specific purpose?",
            "time_stamp": "2024-09-23 20:20:50"
        }
    ],
    "time_stamp": "2024-09-23 20:20:50"
}